dorchester/__init__.py
dorchester/cli.py
dorchester/dotdensity.py
dorchester/output.py
dorchester/point.py
dorchester-0.6.0.dist-info/LICENSE
dorchester-0.6.0.dist-info/METADATA
dorchester-0.6.0.dist-info/WHEEL
dorchester-0.6.0.dist-info/entry_points.txt
dorchester-0.6.0.dist-info/top_level.txt
dorchester-0.6.0.dist-info/RECORD
