Metadata-Version: 2.1
Name: dorchester
Version: 0.6.0
Summary: A toolkit for making dot-density maps in Python
Home-page: https://github.com/eyeseast/dorchester
Author: Chris Amico
License: Apache License, Version 2.0
Project-URL: Issues, https://github.com/eyeseast/dorchester/issues
Project-URL: CI, https://github.com/eyeseast/dorchester/actions
Project-URL: Changelog, https://github.com/eyeseast/dorchester/releases
Platform: UNKNOWN
Requires-Python: >=3.6
License-File: LICENSE
Requires-Dist: click
Requires-Dist: click-default-group
Requires-Dist: fiona
Requires-Dist: geojson
Requires-Dist: numpy
Requires-Dist: shapely
Requires-Dist: tqdm
Provides-Extra: notebooks
Requires-Dist: jupyter ; extra == 'notebooks'
Requires-Dist: matplotlib ; extra == 'notebooks'
Requires-Dist: descartes ; extra == 'notebooks'
Provides-Extra: test
Requires-Dist: pytest ; extra == 'test'
Requires-Dist: pytest-xdist ; extra == 'test'
